ghc/__init__.py
ghc/cli.py
ghc/exceptions.py
ghc/ghc.py
ghc/github.py
ghc/logger.py
ghc/logo.py
ghc/query.py
ghc/reporter.py
ghc/stream.py
ghc/templates/default.j2
ghc/utils.py
ghc-0.2.0.dist-info/entry_points.txt
ghc-0.2.0.dist-info/LICENSE
ghc-0.2.0.dist-info/WHEEL
ghc-0.2.0.dist-info/METADATA
ghc-0.2.0.dist-info/RECORD
