Metadata-Version: 2.1
Name: ghc
Version: 0.2.0
Summary: List up GitHub user / org repositories filtered by topics (ghc = GitHub Collector)
Home-page: https://github.com/homoluctus/ghc
License: MIT
Keywords: GitHub,GraphQL,Jinja2
Author: homoluctus
Author-email: w.slife18sy@gmail.com
Requires-Python: >=3.8,<4.0
Classifier: License :: OSI Approved :: MIT License
Classifier: Programming Language :: Python :: 3
Classifier: Programming Language :: Python :: 3.8
Requires-Dist: Jinja2 (>=2.11.2,<3.0.0)
Requires-Dist: requests (>=2.24.0,<3.0.0)
Project-URL: Repository, https://github.com/homoluctus/ghc
